gpkg.tfserve-0.5.0-py3.5-nspkg.pth
gpkg/tfserve/guild.yml
gpkg/tfserve/serve_image_classifier.py
gpkg.tfserve-0.5.0.dist-info/METADATA
gpkg.tfserve-0.5.0.dist-info/PACKAGE
gpkg.tfserve-0.5.0.dist-info/WHEEL
gpkg.tfserve-0.5.0.dist-info/namespace_packages.txt
gpkg.tfserve-0.5.0.dist-info/top_level.txt
gpkg.tfserve-0.5.0.dist-info/RECORD
