Metadata-Version: 2.1
Name: gpkg.tfserve
Version: 0.5.0
Summary: TFServe support
Home-page: https://github.com/guildai/packages/tree/master/tfserve
Author: Guild AI
Author-email: packages@guild.ai
License: Apache 2.0
Platform: UNKNOWN
Requires-Dist: numpy
Requires-Dist: nose
Requires-Dist: whitenoise
